[
  {
    "需求编号": "R0243",
    "需求描述": "根据村委会财务管理的实际情况，设计标准化的财务管理流程和操作规范，确保财务管理的合规化和规范化。出纳管理提供出纳常用功能，银行日记账、现金日记账，实现在线登记资…",
    "对应页面": "P01 出纳管理-银行存款凭证",
    "原型是否覆盖": "否",
    "问题说明": "缺少功能点: 审批、审核、筛选"
  },
  {
    "需求编号": "R0244",
    "需求描述": "出纳管理日记账中的银行存款凭证查询功能强大，用户能够通过指定特定时间段（如某月份、某季度等）或特定交易特征（如特定交易对手、特定金额范围等），快速在系统内精准定…",
    "对应页面": "P01 出纳管理-银行存款凭证",
    "原型是否覆盖": "是",
    "问题说明": "页面功能点匹配"
  },
  {
    "需求编号": "R0245",
    "需求描述": "该新增功能专为出纳人员日常操作设计，操作流程简便直观。出纳人员在收到新的银行存款业务凭证后，只需在系统中打开新增界面，按照提示依次填入如凭证日期、交易金额、对方…",
    "对应页面": "P01 出纳管理-银行存款凭证",
    "原型是否覆盖": "是",
    "问题说明": "页面功能点匹配"
  },
  {
    "需求编号": "R0246",
    "需求描述": "出纳管理日记账的银行存款凭证导出功能提供了丰富的文件格式选择，如Excel、PDF等。当用户需要对银行存款凭证数据进行深入分析时，可将数据导出为Excel格式，…",
    "对应页面": "P01 出纳管理-银行存款凭证",
    "原型是否覆盖": "否",
    "问题说明": "缺少功能点: 排序、筛选"
  },
  {
    "需求编号": "R0247",
    "需求描述": "删除功能在维护数据准确性和整洁性方面至关重要。当财务人员发现银行存款凭证存在录入错误（如金额错误、账户信息错误等）或凭证已过期失效（如交易取消、凭证重复等情况）…",
    "对应页面": "P01 出纳管理-银行存款凭证",
    "原型是否覆盖": "是",
    "问题说明": "页面功能点匹配"
  },
  {
    "需求编号": "R0248",
    "需求描述": "为用户提供银行存款凭证导入的标准模板，确保导入数据的格式一致性和准确性。模板可以明确规定所需的字段信息，如交易日期、交易金额、对方账户信息等，同时提供填写说明和…",
    "对应页面": "P01 出纳管理-银行存款凭证",
    "原型是否覆盖": "是",
    "问题说明": "页面功能点匹配"
  },
  {
    "需求编号": "R0249",
    "需求描述": "系统能够根据银行存款交易数据自动生成凭证，减少人工录入的工作量和错误率。自动生成的凭证可以包括交易日期、交易金额、摘要等基本信息，并根据预设的会计科目规则进行科…",
    "对应页面": "P01 出纳管理-银行存款凭证",
    "原型是否覆盖": "否",
    "问题说明": "缺少功能点: 审批、审核"
  },
  {
    "需求编号": "R0250",
    "需求描述": "以列表形式展示银行存款凭证的详细信息，包括凭证编号、交易日期、交易金额、对方账户等。列表可以进行排序和筛选，方便用户快速查找特定的凭证。同时，列表中的每一行凭证…",
    "对应页面": "P01 出纳管理-银行存款凭证",
    "原型是否覆盖": "否",
    "问题说明": "缺少功能点: 排序、筛选"
  },
  {
    "需求编号": "R0251",
    "需求描述": "出纳管理日记账中，库存现金凭证新增功能用于及时录入现金收支业务信息，填写交易日期、金额、用途等并选择会计科目，系统自动记录相关信息，保障现金交易数据实时更新。",
    "对应页面": "P02 出纳管理-库存现金凭证",
    "原型是否覆盖": "是",
    "问题说明": "页面功能点匹配"
  },
  {
    "需求编号": "R0252",
    "需求描述": "该功能便于批量处理现金凭证数据，可下载模板并按要求填写后导入，系统校验数据格式和逻辑，提高录入效率，减少人工错误。",
    "对应页面": "P02 出纳管理-库存现金凭证",
    "原型是否覆盖": "否",
    "问题说明": "缺少功能点: 导入"
  },
  {
    "需求编号": "R0253",
    "需求描述": "用户可将库存现金凭证数据导出为常见格式，能按需选择格式和范围，导出文件含详细信息，方便离线分析、共享、存档与备份。",
    "对应页面": "P02 出纳管理-库存现金凭证",
    "原型是否覆盖": "是",
    "问题说明": "页面功能点匹配"
  },
  {
    "需求编号": "R0254",
    "需求描述": "查询功能提供多维度条件，用户依日期、金额、摘要关键词、对方科目等组合查询，结果列表展示详细信息，助于核对收支、查找明细。",
    "对应页面": "P02 出纳管理-库存现金凭证",
    "原型是否覆盖": "是",
    "问题说明": "页面功能点匹配"
  },
  {
    "需求编号": "R0255",
    "需求描述": "主要清理错误或过期现金凭证数据，删除前需确认，防止误删，系统清除记录并留存操作日志，以便审计追溯。",
    "对应页面": "P02 出纳管理-库存现金凭证",
    "原型是否覆盖": "否",
    "问题说明": "缺少功能点: 删除"
  },
  {
    "需求编号": "R0256",
    "需求描述": "根据库存现金交易数据自动生成凭证，提高工作效率和准确性。自动生成的凭证可以包括现金收支的日期、金额、用途等信息，并按照会计科目规则进行科目分配。用户可以对自动生…",
    "对应页面": "P02 出纳管理-库存现金凭证",
    "原型是否覆盖": "否",
    "问题说明": "缺少功能点: 审批、自动生成凭证"
  },
  {
    "需求编号": "R0257",
    "需求描述": "以列表形式展示库存现金凭证的详细信息，方便用户查看和管理现金交易记录。列表可以进行排序和筛选，用户可以点击每一行凭证查看详细信息，如凭证附件、现金收支明细等。",
    "对应页面": "P02 出纳管理-库存现金凭证",
    "原型是否覆盖": "否",
    "问题说明": "缺少功能点: 排序、筛选"
  },
  {
    "需求编号": "R0258",
    "需求描述": "以列表形式展示库存现金凭证的详细信息，方便用户查看和管理现金交易记录。列表可以进行排序和筛选，用户可以点击每一行凭证查看详细信息，如凭证附件、现金收支明细等。汇…",
    "对应页面": "P02 出纳管理-库存现金凭证",
    "原型是否覆盖": "否",
    "问题说明": "缺少功能点: 排序、筛选"
  },
  {
    "需求编号": "R0259",
    "需求描述": "出纳管理资金报表的账户汇总列表查询便捷，用户可依账户名称、余额范围、账户类别等条件精准定位数据，为财务分析与资金管理提供有力支持。",
    "对应页面": "P03 出纳管理-资金报表与账户汇总",
    "原型是否覆盖": "否",
    "问题说明": "缺少功能点: 查询"
  },
  {
    "需求编号": "R0260",
    "需求描述": "此打印功能操作简便，用户可调整打印页面布局，打印内容涵盖关键信息，方便纸质存档与财务审核，助力财务工作规范化管理。",
    "对应页面": "P03 出纳管理-资金报表与账户汇总",
    "原型是否覆盖": "否",
    "问题说明": "缺少功能点: 审批、审核、打印"
  },
  {
    "需求编号": "R0261",
    "需求描述": "账户汇总列表导出功能强大，支持导出Excel格式数据，包含详细账户信息，便于在Excel中深入分析，为财务决策提供更坚实的数据依据。",
    "对应页面": "P03 出纳管理-资金报表与账户汇总",
    "原型是否覆盖": "否",
    "问题说明": "缺少功能点: 导出"
  },
  {
    "需求编号": "R0262",
    "需求描述": "按照收支类别对村集体的资金流动进行汇总，展示不同收支类型的金额、占比等信息。例如，可以将收支分为经营收入、经营支出、补助收入等类别，帮助用户了解村集体的资金来源…",
    "对应页面": "P03 出纳管理-资金报表与账户汇总",
    "原型是否覆盖": "是",
    "问题说明": "RTM已映射到页面，需求为综合描述"
  },
  {
    "需求编号": "R0263",
    "需求描述": "在出纳管理资金报表中，收支类别汇总列表查询功能可帮助用户快速查找所需的收支类别数据。用户可以通过设定时间范围来筛选出特定时间段内的收支类别数据，也可以根据不同的…",
    "对应页面": "P03 出纳管理-资金报表与账户汇总",
    "原型是否覆盖": "否",
    "问题说明": "缺少功能点: 查询、筛选"
  },
  {
    "需求编号": "R0264",
    "需求描述": "收支类别汇总列表导出功能使用户能够将数据导出为常见的文件格式，如Excel等。导出的数据包含了详细的收支类别信息，例如收入金额、支出金额、收入笔数、支出笔数等。…",
    "对应页面": "P03 出纳管理-资金报表与账户汇总",
    "原型是否覆盖": "否",
    "问题说明": "缺少功能点: 导出"
  },
  {
    "需求编号": "R0265",
    "需求描述": "此打印功能方便用户将收支类别汇总列表以纸质形式呈现。用户可以在系统中操作打印按钮，将当前查询到的收支类别汇总数据打印出来。打印出来的报表格式规范，便于财务人员进…",
    "对应页面": "P03 出纳管理-资金报表与账户汇总",
    "原型是否覆盖": "否",
    "问题说明": "缺少功能点: 审批、审核、打印、查询"
  },
  {
    "需求编号": "R0266",
    "需求描述": "允许用户新增现金账户信息，包括账户名称、初始余额、备注等。新增现金账户可以满足村集体财务管理的需要，方便对现金收支进行单独管理。",
    "对应页面": "P03 出纳管理-资金报表与账户汇总",
    "原型是否覆盖": "否",
    "问题说明": "缺少功能点: 新增"
  },
  {
    "需求编号": "R0267",
    "需求描述": "以列表形式展示村集体的现金账户信息，包括账户名称、余额、交易明细等。用户可以通过列表快速查看现金账户的状态，进行现金管理和核对。",
    "对应页面": "P03 出纳管理-资金报表与账户汇总",
    "原型是否覆盖": "是",
    "问题说明": "RTM已映射到页面，需求为综合描述"
  },
  {
    "需求编号": "R0268",
    "需求描述": "与现金账户新增类似，用于新增银行账户信息。用户可以输入银行账户名称、开户行、账号等信息，确保银行账户信息的准确性和完整性。",
    "对应页面": "P03 出纳管理-资金报表与账户汇总",
    "原型是否覆盖": "否",
    "问题说明": "缺少功能点: 新增"
  },
  {
    "需求编号": "R0269",
    "需求描述": "展示村集体的银行账户信息，方便用户管理银行账户。列表可以显示账户名称、开户行、账号、余额等信息，用户可以点击每一个银行账户查看详细的交易记录和对账单。",
    "对应页面": "P03 出纳管理-资金报表与账户汇总",
    "原型是否覆盖": "是",
    "问题说明": "RTM已映射到页面，需求为综合描述"
  },
  {
    "需求编号": "R0270",
    "需求描述": "提供收入模版列表，方便出纳人员在录入收入凭证时选择合适的模版。收入模版可以包括不同类型的收入，如经营收入、补助收入等，每个模版可以预设摘要、会计科目等信息，提高…",
    "对应页面": "P04 出纳管理-收入/支出模板",
    "原型是否覆盖": "否",
    "问题说明": "缺少功能点: 新增"
  },
  {
    "需求编号": "R0271",
    "需求描述": "允许用户新增收入模版，根据村集体的实际收入情况进行自定义设置。用户可以输入模版名称、摘要、会计科目等信息，创建符合村集体财务管理需求的收入模版。",
    "对应页面": "P04 出纳管理-收入/支出模板",
    "原型是否覆盖": "否",
    "问题说明": "缺少功能点: 新增"
  },
  {
    "需求编号": "R0272",
    "需求描述": "与收入模版列表类似，展示支出模版信息。支出模版可以包括不同类型的支出，如经营支出、管理费用等，帮助出纳人员快速录入支出凭证。",
    "对应页面": "P04 出纳管理-收入/支出模板",
    "原型是否覆盖": "否",
    "问题说明": "缺少功能点: 新增"
  },
  {
    "需求编号": "R0273",
    "需求描述": "在出纳管理中，出纳模版支出查询功能允许用户通过设定条件来查找所需的支出模版。用户可以依据支出类型、金额范围进行筛选，快速定位到符合村集体实际需求的支出模版，方便…",
    "对应页面": "P04 出纳管理-收入/支出模板",
    "原型是否覆盖": "是",
    "问题说明": "页面功能点匹配"
  },
  {
    "需求编号": "R0274",
    "需求描述": "出纳管理出纳模版支出新增功能主要是为了满足村集体特殊支出需求而设计。当村集体有新的、不在现有模版中的支出类型时，用户可以通过此功能添加新的支出模版。在新增界面中…",
    "对应页面": "P04 出纳管理-收入/支出模板",
    "原型是否覆盖": "否",
    "问题说明": "缺少功能点: 新增"
  },
  {
    "需求编号": "R0275",
    "需求描述": "出纳管理中的内部转账查询功能，方便用户在众多内部转账记录中快速定位所需信息。用户可以根据不同的条件进行查询，比如按照转账日期范围查找特定时间段内的转账记录，或者…",
    "对应页面": "P05 出纳管理-内部转账",
    "原型是否覆盖": "否",
    "问题说明": "缺少功能点: 筛选"
  },
  {
    "需求编号": "R0276",
    "需求描述": "当出现内部转账记录错误的情况时，出纳管理的内部转账删除功能就可以派上用场。例如，转账金额录入错误或者转账账户选错等情况，财务人员可以通过此功能将错误的转账记录删…",
    "对应页面": "P05 出纳管理-内部转账",
    "原型是否覆盖": "否",
    "问题说明": "缺少功能点: 删除、新增"
  },
  {
    "需求编号": "R0277",
    "需求描述": "内部转账导出功能能够将村集体的内部转账数据转换为Excel等常见格式。这样一来，用户可以把导出的数据在Excel软件中进行进一步分析，例如通过数据透视表来统计各…",
    "对应页面": "P05 出纳管理-内部转账",
    "原型是否覆盖": "是",
    "问题说明": "页面功能点匹配"
  },
  {
    "需求编号": "R0278",
    "需求描述": "根据内部转账记录自动生成凭证，提高财务管理的效率和准确性。生成的凭证可以包括转账日期、转出账户、转入账户、金额等信息，并按照会计科目规则进行科目分配。",
    "对应页面": "P05 出纳管理-内部转账",
    "原型是否覆盖": "否",
    "问题说明": "缺少功能点: 自动生成凭证"
  },
  {
    "需求编号": "R0279",
    "需求描述": "提供出纳初始化模版的查询功能，方便用户在系统初始化时查找合适的模版。出纳初始化模版可以包括账户信息、期初余额、凭证设置等内容，帮助用户快速完成系统的初始化工作。",
    "对应页面": "P06 出纳管理-初始化模板",
    "原型是否覆盖": "是",
    "问题说明": "页面功能点匹配"
  },
  {
    "需求编号": "R0280",
    "需求描述": "以列表形式展示出纳初始化模版，用户可以选择适合村集体的模版进行初始化设置。列表可以显示模版名称、适用范围、创建时间等信息，方便用户进行选择和比较。",
    "对应页面": "P06 出纳管理-初始化模板",
    "原型是否覆盖": "否",
    "问题说明": "缺少功能点: 新增"
  },
  {
    "需求编号": "R0281",
    "需求描述": "允许用户根据村集体的实际情况新增出纳初始化模版。用户可以自定义模版的内容，包括账户设置、期初余额录入、凭证格式等，满足村集体的个性化需求。",
    "对应页面": "P06 出纳管理-初始化模板",
    "原型是否覆盖": "否",
    "问题说明": "缺少功能点: 新增"
  },
  {
    "需求编号": "R0282",
    "需求描述": "出纳管理中，可对出纳初始化模版进行创建、编辑、删除、复制及权限设置等操作，创建时需填详细信息并经系统验证，编辑能应对多种变化且可选版本管理，删除需特定权限与确认…",
    "对应页面": "P06 出纳管理-初始化模板",
    "原型是否覆盖": "否",
    "问题说明": "缺少功能点: 修改、删除、新增"
  },
  {
    "需求编号": "R0283",
    "需求描述": "出纳管理里的出纳初始化模版统计功能，会按不同维度统计模版数量、使用频率及更新情况，可能用图表展示并提供交互功能，统计数据可用于优化模版、合理分配资源及防范财务风…",
    "对应页面": "P06 出纳管理-初始化模板",
    "原型是否覆盖": "是",
    "问题说明": "RTM已映射到页面，需求为综合描述"
  },
  {
    "需求编号": "R0284",
    "需求描述": "出纳管理中的出纳对账查询功能，能够让用户依据时间段、账户类型等条件进行查询。通过设定这些条件，用户可以快速定位到所需的对账数据，方便查看相关账户的收支情况，确保…",
    "对应页面": "P07 出纳管理-出纳对账",
    "原型是否覆盖": "是",
    "问题说明": "页面功能点匹配"
  },
  {
    "需求编号": "R0285",
    "需求描述": "此打印功能方便用户将出纳对账结果以纸质形式呈现。在完成对账查询后，用户可使用打印功能将当前的对账结果打印出来。打印出的报表格式规范，便于财务人员进行审核，确保每…",
    "对应页面": "P07 出纳管理-出纳对账",
    "原型是否覆盖": "否",
    "问题说明": "缺少功能点: 审批、审核"
  },
  {
    "需求编号": "R0286",
    "需求描述": "出纳对账导出功能可将对账数据转换为Excel等常见格式。用户通过此功能导出数据后，可以在Excel中进行深入分析，例如利用函数和数据透视表来分析不同账户在特定时…",
    "对应页面": "P07 出纳管理-出纳对账",
    "原型是否覆盖": "是",
    "问题说明": "页面功能点匹配"
  },
  {
    "需求编号": "R0287",
    "需求描述": "在出纳对账过程中，显示未审核的凭证信息，提醒用户进行审核。未审核凭证可能存在错误或不完整的情况，需要用户进行检查和处理，确保财务数据的准确性和合规性。",
    "对应页面": "P07 出纳管理-出纳对账",
    "原型是否覆盖": "否",
    "问题说明": "缺少功能点: 审批、审核"
  },
  {
    "需求编号": "R0288",
    "需求描述": "提供只显示已生成凭证的查询功能，方便用户在对账时快速查找已生成的凭证进行核对。已生成凭证是经过系统自动生成或人工录入并保存的凭证，具有较高的可靠性和准确性，可以…",
    "对应页面": "P08 凭证管理-记账凭证",
    "原型是否覆盖": "否",
    "问题说明": "缺少功能点: 修改、审批、审核、新增"
  },
  {
    "需求编号": "R0289",
    "需求描述": "允许用户在记账凭证中新增会计科目，满足村集体财务管理的特殊需求。新增科目可以根据业务类型、资金性质等进行分类，方便用户进行科目选择和记账。",
    "对应页面": "P08 凭证管理-记账凭证",
    "原型是否覆盖": "否",
    "问题说明": "缺少功能点: 新增"
  },
  {
    "需求编号": "R0290",
    "需求描述": "在录入记账凭证后，用户可以选择保存并新增功能，快速进入下一张凭证的录入界面，提高工作效率。保存并新增功能可以确保当前凭证的信息被正确保存，同时为用户提供便捷的方…",
    "对应页面": "P08 凭证管理-记账凭证",
    "原型是否覆盖": "否",
    "问题说明": "缺少功能点: 新增"
  },
  {
    "需求编号": "R0291",
    "需求描述": "用户可以在记账凭证中添加备注信息，对凭证的特殊情况或重要事项进行说明。备注信息可以帮助其他财务人员更好地理解凭证的内容和背景，提高财务数据的可读性和可追溯性。",
    "对应页面": "P08 凭证管理-记账凭证",
    "原型是否覆盖": "是",
    "问题说明": "RTM已映射到页面，需求为综合描述"
  },
  {
    "需求编号": "R0292",
    "需求描述": "支持用户上传与记账凭证相关的附件，如发票、收据、合同等。附件上传功能可以确保财务凭证的真实性和完整性，方便日后的审计和查询。",
    "对应页面": "P08 凭证管理-记账凭证",
    "原型是否覆盖": "是",
    "问题说明": "页面功能点匹配"
  },
  {
    "需求编号": "R0293",
    "需求描述": "用户可以在记账凭证中记录附单据的数量，便于核对凭证与附件的一致性。附单据数量的记录可以帮助用户快速查找和整理相关附件，提高财务工作的效率和准确性。",
    "对应页面": "P08 凭证管理-记账凭证",
    "原型是否覆盖": "否",
    "问题说明": "缺少功能点: 附单据数量"
  },
  {
    "需求编号": "R0294",
    "需求描述": "提供查看凭证打印设置的功能，用户可以根据需要调整凭证的打印格式、纸张大小、字体等参数。打印设置功能可以确保凭证打印的美观和规范，满足不同用户的需求。",
    "对应页面": "P08 凭证管理-记账凭证",
    "原型是否覆盖": "否",
    "问题说明": "缺少功能点: 打印设置"
  },
  {
    "需求编号": "R0295",
    "需求描述": "用户可以直接打印记账凭证，方便纸质存档和审核。打印功能可以选择单张凭证打印或批量打印，提高工作效率。",
    "对应页面": "P08 凭证管理-记账凭证",
    "原型是否覆盖": "否",
    "问题说明": "缺少功能点: 审批、审核"
  },
  {
    "需求编号": "R0296",
    "需求描述": "对记账凭证进行审核，确保凭证的准确性和合规性。审核功能可以由具有审核权限的用户进行操作，审核通过的凭证将被标记为已审核状态，未经审核或审核不通过的凭证需要进行修…",
    "对应页面": "P08 凭证管理-记账凭证",
    "原型是否覆盖": "否",
    "问题说明": "缺少功能点: 修改、审批、审核、新增"
  },
  {
    "需求编号": "R0297",
    "需求描述": "在必要时，用户可以对已审核的凭证进行反审核操作。反审核功能可以在发现凭证错误或需要进行修改时使用，但需要谨慎操作，确保反审核后的凭证能够正确反映财务状况。",
    "对应页面": "P08 凭证管理-记账凭证",
    "原型是否覆盖": "否",
    "问题说明": "缺少功能点: 修改、反审核、审批、审核"
  },
  {
    "需求编号": "R0298",
    "需求描述": "将记账凭证导出为常见的文件格式，如Excel、PDF等，方便进行离线分析、存档或与其他系统进行数据交换。导出功能可以选择单张凭证导出或批量导出，提高数据处理的效…",
    "对应页面": "P08 凭证管理-记账凭证",
    "原型是否覆盖": "是",
    "问题说明": "页面功能点匹配"
  },
  {
    "需求编号": "R0299",
    "需求描述": "对已录入的记账凭证进行修改，以纠正错误或更新信息。修改功能需要在凭证未审核或反审核的状态下进行，确保修改后的凭证能够符合财务规范和要求。",
    "对应页面": "P08 凭证管理-记账凭证",
    "原型是否覆盖": "否",
    "问题说明": "缺少功能点: 修改、反审核、审批、审核、新增"
  },
  {
    "需求编号": "R0300",
    "需求描述": "在记账凭证列表中插入新的凭证，方便用户在特定位置添加凭证。插入功能可以根据业务需求进行灵活操作，提高凭证录入的准确性和完整性。",
    "对应页面": "P08 凭证管理-记账凭证",
    "原型是否覆盖": "否",
    "问题说明": "缺少功能点: 插入、新增"
  },
  {
    "需求编号": "R0301",
    "需求描述": "与凭证管理记账凭证附单据数量功能类似，用户可以查看凭证所附单据的数量，确保凭证与附件的一致性。",
    "对应页面": "P08 凭证管理-记账凭证",
    "原型是否覆盖": "否",
    "问题说明": "缺少功能点: 附单据数量"
  },
  {
    "需求编号": "R0302",
    "需求描述": "提供强大的凭证查询功能，用户可以根据凭证编号、日期、科目、金额等条件进行查询。查询结果可以以列表形式展示，用户可以点击每一张凭证查看详细信息，方便进行财务分析和…",
    "对应页面": "P08 凭证管理-记账凭证",
    "原型是否覆盖": "是",
    "问题说明": "页面功能点匹配"
  },
  {
    "需求编号": "R0303",
    "需求描述": "对删除的凭证进行管理，用户可以在凭证回收站中查询已删除的凭证信息。回收站查询功能可以帮助用户在误删凭证时进行恢复，确保财务数据的安全性和完整性。",
    "对应页面": "P09 凭证管理-凭证回收站",
    "原型是否覆盖": "否",
    "问题说明": "缺少功能点: 删除、回收站查询"
  },
  {
    "需求编号": "R0304",
    "需求描述": "将回收站中的凭证还原到正常状态，恢复被删除的凭证数据。还原功能需要谨慎操作，确保还原后的凭证能够正确反映财务状况。",
    "对应页面": "P09 凭证管理-凭证回收站",
    "原型是否覆盖": "否",
    "问题说明": "缺少功能点: 删除、回收站查询、还原"
  },
  {
    "需求编号": "R0305",
    "需求描述": "对回收站中的凭证进行彻底删除，释放存储空间。彻底删除功能需要在确认凭证不再需要时使用，以避免误删重要数据。",
    "对应页面": "P09 凭证管理-凭证回收站",
    "原型是否覆盖": "否",
    "问题说明": "缺少功能点: 删除、回收站查询、彻底删除"
  },
  {
    "需求编号": "R0306",
    "需求描述": "以列表形式展示回收站中的凭证信息，方便用户进行管理和操作。列表可以显示凭证编号、日期、科目、金额等信息，用户可以对回收站中的凭证进行还原或彻底删除操作。为村委会…",
    "对应页面": "P09 凭证管理-凭证回收站",
    "原型是否覆盖": "否",
    "问题说明": "缺少功能点: 删除、反结账、回收站查询、彻底删除、结账、还原"
  },
  {
    "需求编号": "R0307",
    "需求描述": "用户可以选择要进行结账的会计期间，确保结账操作的准确性和及时性。会计期间的选择可以根据村集体的财务报表周期进行设置，如月度、季度、年度等。",
    "对应页面": "P10 期末处理-月结与反结账",
    "原型是否覆盖": "否",
    "问题说明": "缺少功能点: 反结账、结账"
  },
  {
    "需求编号": "R0308",
    "需求描述": "在结账前进行期末处理，包括结转损益、计提折旧、摊销费用等。期末处理功能可以确保财务数据的完整性和准确性，为结账做好准备。",
    "对应页面": "P10 期末处理-月结与反结账",
    "原型是否覆盖": "否",
    "问题说明": "缺少功能点: 反结账、结账"
  },
  {
    "需求编号": "R0309",
    "需求描述": "对结转科目的设置进行管理，用户可以根据村集体的财务制度和业务需求进行配置。结转科目配置功能可以确保结转操作的准确性和合规性。",
    "对应页面": "P10 期末处理-月结与反结账",
    "原型是否覆盖": "否",
    "问题说明": "缺少功能点: 反结账、结账、配置"
  },
  {
    "需求编号": "R0310",
    "需求描述": "选择损益凭证的类型，如收入凭证、支出凭证等。损益凭证类型的选择可以根据村集体的财务报表要求进行设置，确保损益计算的准确性。",
    "对应页面": "P10 期末处理-月结与反结账",
    "原型是否覆盖": "否",
    "问题说明": "缺少功能点: 反结账、结账"
  },
  {
    "需求编号": "R0311",
    "需求描述": "在进行结转操作前，进行结转试算，检查结转数据的准确性和完整性。结转试算功能可以帮助用户发现潜在的错误和问题，及时进行调整和修正。",
    "对应页面": "P10 期末处理-月结与反结账",
    "原型是否覆盖": "否",
    "问题说明": "缺少功能点: 反结账、结账"
  },
  {
    "需求编号": "R0312",
    "需求描述": "允许用户自定义结转模版，根据村集体的特殊业务需求进行设置。自定义结转模版可以提高结转操作的效率和准确性，减少人工操作的错误率。",
    "对应页面": "P10 期末处理-月结与反结账",
    "原型是否覆盖": "否",
    "问题说明": "缺少功能点: 反结账、结账"
  },
  {
    "需求编号": "R0313",
    "需求描述": "对选定的会计期间进行月结操作，将本月的财务数据进行汇总和结算，生成月度财务报表。月结功能可以确保财务数据的及时性和准确性，为村集体的财务管理提供可靠的依据。",
    "对应页面": "P10 期末处理-月结与反结账",
    "原型是否覆盖": "否",
    "问题说明": "缺少功能点: 反结账、结账"
  },
  {
    "需求编号": "R0314",
    "需求描述": "在必要时，用户可以对已结账的会计期间进行反结账操作。反结账功能可以在发现结账错误或需要进行调整时使用，但需要谨慎操作，确保反结账后的财务数据能够正确反映村集体的…",
    "对应页面": "P10 期末处理-月结与反结账",
    "原型是否覆盖": "否",
    "问题说明": "缺少功能点: 反结账、结账"
  },
  {
    "需求编号": "R0315",
    "需求描述": "对多个会计期间进行批量反结账操作，提高工作效率。批量反结功能需要在确认多个会计期间存在错误或需要进行调整时使用，确保反结账后的财务数据能够正确反映村集体的财务状…",
    "对应页面": "P10 期末处理-月结与反结账",
    "原型是否覆盖": "否",
    "问题说明": "缺少功能点: 反结账、结账"
  },
  {
    "需求编号": "R0316",
    "需求描述": "按照时间顺序记录村集体的每一笔财务交易，形成序时账。序时账可以方便用户查看财务交易的发生时间、金额、科目等信息，为财务分析和审计提供基础数据。",
    "对应页面": "P11 账簿-序时账",
    "原型是否覆盖": "是",
    "问题说明": "RTM已映射到页面，需求为综合描述"
  },
  {
    "需求编号": "R0317",
    "需求描述": "在序时账列表中，用户可以查看每一条记录，穿透查看对应的记账凭证详情。凭证详情包括凭证编号、日期、科目、金额、附件等信息，方便用户进行财务核对和审计。",
    "对应页面": "P11 账簿-序时账",
    "原型是否覆盖": "是",
    "问题说明": "RTM已映射到页面，需求为综合描述"
  },
  {
    "需求编号": "R0318",
    "需求描述": "与凭证详情穿透功能类似，用户可以直接在序时账列表中查看每一条记录对应的凭证详情，无需点击穿透。",
    "对应页面": "P11 账簿-序时账",
    "原型是否覆盖": "是",
    "问题说明": "RTM已映射到页面，需求为综合描述"
  },
  {
    "需求编号": "R0319",
    "需求描述": "序时账应提供强大的查询功能，用户可以根据多种条件进行组合查询，如日期范围、科目、金额、摘要关键词等。查询结果应能够快速准确地呈现，并且可以进行排序和筛选，方便用…",
    "对应页面": "P11 账簿-序时账",
    "原型是否覆盖": "是",
    "问题说明": "页面功能点匹配"
  },
  {
    "需求编号": "R0320",
    "需求描述": "展示村集体各个会计科目的余额情况。科目余额表可以按照科目编码或名称进行排序，清晰地显示每个科目的期初余额、本期借方发生额、本期贷方发生额和期末余额。用户可以通过…",
    "对应页面": "P12 账簿-科目余额表",
    "原型是否覆盖": "是",
    "问题说明": "页面功能点匹配"
  },
  {
    "需求编号": "R0321",
    "需求描述": "账簿科目余额表管理功能丰富多样，除保障科目余额数据的实时同步与准确更新，提供纠错调整机制外，还能进行多维度分析，如基于历史数据的趋势分析与可自定义的预警设置，以…",
    "对应页面": "P12 账簿-科目余额表",
    "原型是否覆盖": "是",
    "问题说明": "RTM已映射到页面，需求为综合描述"
  },
  {
    "需求编号": "R0322",
    "需求描述": "除了基本的科目余额查询功能外，还应提供更多的查询选项。例如，用户可以选择特定的会计期间进行查询，查看不同时间段内各个科目的余额变化情况；或者按照科目级别进行查询…",
    "对应页面": "P12 账簿-科目余额表",
    "原型是否覆盖": "是",
    "问题说明": "页面功能点匹配"
  },
  {
    "需求编号": "R0323",
    "需求描述": "科目余额表应支持导出功能。导出功能允许用户将科目余额表导出为Excel、PDF等格式的文件，以便在其他软件中进行进一步的分析和处理。导出的文件应保持与科目余额表…",
    "对应页面": "P12 账簿-科目余额表",
    "原型是否覆盖": "是",
    "问题说明": "页面功能点匹配"
  },
  {
    "需求编号": "R0324",
    "需求描述": "打印方向为纵向，纸张大小选择A4，页面边距设置为左边40毫米、右边10毫米、上边50毫米、下边45毫米，编制单位需用户自行输入，若不输入则为默认，打印日期为20…",
    "对应页面": "P12 账簿-科目余额表",
    "原型是否覆盖": "是",
    "问题说明": "页面功能点匹配"
  },
  {
    "需求编号": "R0325",
    "需求描述": "对村集体的记账凭证进行科目汇总，展示各个科目的借贷方发生额合计。科目汇总表可以帮助用户快速了解村集体在一定时期内的财务活动情况，为编制财务报表提供基础数据。",
    "对应页面": "P13 账簿-科目汇总表",
    "原型是否覆盖": "是",
    "问题说明": "RTM已映射到页面，需求为综合描述"
  },
  {
    "需求编号": "R0326",
    "需求描述": "科目汇总表应提供查询功能，用户可以根据日期范围、科目等条件进行查询。查询结果应能够快速准确地呈现，并且可以进行排序和筛选。打印功能可以将科目汇总表以纸质形式输出…",
    "对应页面": "P13 账簿-科目汇总表",
    "原型是否覆盖": "否",
    "问题说明": "缺少功能点: 审批、审核"
  },
  {
    "需求编号": "R0327",
    "需求描述": "在打印科目汇总表时，用户可以根据自己的需求进行打印详情的调整。例如，用户可以选择打印的纸张大小、方向、边距等参数；可以设置打印的标题、页眉、页脚等内容；还可以选…",
    "对应页面": "P13 账簿-科目汇总表",
    "原型是否覆盖": "是",
    "问题说明": "页面功能点匹配"
  },
  {
    "需求编号": "R0328",
    "需求描述": "科目汇总表应支持导出功能，用户可以将其导出为Excel、PDF等格式的文件，以便在其他软件中进行进一步的分析和处理。导出的文件应保持与科目汇总表页面显示的格式一…",
    "对应页面": "P13 账簿-科目汇总表",
    "原型是否覆盖": "是",
    "问题说明": "页面功能点匹配"
  },
  {
    "需求编号": "R0329",
    "需求描述": "详细记录村集体每个会计科目的明细交易情况。明细账可以按照时间顺序展示每一笔交易的日期、凭证编号、摘要、借方金额、贷方金额等信息，让用户能够深入了解每个科目的具体…",
    "对应页面": "P14 账簿-明细账",
    "原型是否覆盖": "是",
    "问题说明": "RTM已映射到页面，需求为综合描述"
  },
  {
    "需求编号": "R0330",
    "需求描述": "明细账应提供查询功能，用户可以根据多种条件进行组合查询，如科目、日期范围、金额、摘要关键词等。查询结果应能够快速准确地呈现，并且可以进行排序和筛选。",
    "对应页面": "P14 账簿-明细账",
    "原型是否覆盖": "是",
    "问题说明": "页面功能点匹配"
  },
  {
    "需求编号": "R0331",
    "需求描述": "导出功能允许用户将明细账数据导出为Excel、PDF等格式的文件，以便进行离线分析、存档或与其他系统进行数据交换。",
    "对应页面": "P14 账簿-明细账",
    "原型是否覆盖": "是",
    "问题说明": "页面功能点匹配"
  },
  {
    "需求编号": "R0332",
    "需求描述": "打印功能可以将明细账以纸质形式输出，方便用户进行审核和存档。",
    "对应页面": "P14 账簿-明细账",
    "原型是否覆盖": "否",
    "问题说明": "缺少功能点: 审批、审核"
  },
  {
    "需求编号": "R0333",
    "需求描述": "以总分类的形式展示村集体的财务状况，包括各个会计科目的期初余额、本期发生额和期末余额。总分类账可以帮助用户快速了解村集体的整体财务状况，为财务决策提供宏观的视角…",
    "对应页面": "P15 账簿-总分类账",
    "原型是否覆盖": "是",
    "问题说明": "RTM已映射到页面，需求为综合描述"
  },
  {
    "需求编号": "R0334",
    "需求描述": "总分类账应提供查询功能，用户可以根据日期范围、科目等条件进行查询。查询结果应能够快速准确地呈现，并且可以进行排序和筛选",
    "对应页面": "P15 账簿-总分类账",
    "原型是否覆盖": "否",
    "问题说明": "缺少功能点: 排序"
  },
  {
    "需求编号": "R0335",
    "需求描述": "导出功能允许用户将总分类账数据导出为Excel、PDF等格式的文件，以便在其他软件中进行进一步的分析和处理。",
    "对应页面": "P15 账簿-总分类账",
    "原型是否覆盖": "否",
    "问题说明": "缺少功能点: 导出"
  },
  {
    "需求编号": "R0336",
    "需求描述": "打印功能可以将总分类账以纸质形式输出，方便用户进行审核和存档。",
    "对应页面": "P15 账簿-总分类账",
    "原型是否覆盖": "否",
    "问题说明": "缺少功能点: 审批、审核、打印"
  },
  {
    "需求编号": "R0337",
    "需求描述": "结合总账和日记账的特点，展示村集体的财务交易记录和科目余额情况。总账日记账可以让用户在一个页面上同时查看交易记录和对应的科目余额，方便进行财务核对和分析。",
    "对应页面": "P16 账簿-总账日记账",
    "原型是否覆盖": "是",
    "问题说明": "RTM已映射到页面，需求为综合描述"
  },
  {
    "需求编号": "R0338",
    "需求描述": "总账日记账应提供查询功能，用户可以根据多种条件进行组合查询，如日期范围、科目、金额等。查询结果应能够快速准确地呈现，并且可以进行排序和筛选。",
    "对应页面": "P16 账簿-总账日记账",
    "原型是否覆盖": "否",
    "问题说明": "缺少功能点: 排序、查询、筛选"
  },
  {
    "需求编号": "R0339",
    "需求描述": "导出功能允许用户将总账日记账数据导出为Excel、PDF等格式的文件，以便进行离线分析、存档或与其他系统进行数据交换。",
    "对应页面": "P16 账簿-总账日记账",
    "原型是否覆盖": "否",
    "问题说明": "缺少功能点: 导出"
  },
  {
    "需求编号": "R0340",
    "需求描述": "打印功能可以将总账日记账以纸质形式输出，方便用户进行审核和存档。",
    "对应页面": "P16 账簿-总账日记账",
    "原型是否覆盖": "否",
    "问题说明": "缺少功能点: 审批、审核、打印"
  },
  {
    "需求编号": "R0341",
    "需求描述": "详细展示村集体的收入和支出情况，包括收入来源、支出项目、金额等信息。收支明细表可以帮助用户了解村集体的资金流动情况，为预算编制和成本控制提供依据。",
    "对应页面": "P17 账簿-收支明细表",
    "原型是否覆盖": "否",
    "问题说明": "模块不一致：RTM=财务中心, 页面结构=报表中心"
  },
  {
    "需求编号": "R0342",
    "需求描述": "收支明细表应提供查询功能，用户可以根据日期范围、收入来源、支出项目等条件进行查询。查询结果应能够快速准确地呈现，并且可以进行排序和筛选。",
    "对应页面": "P17 账簿-收支明细表",
    "原型是否覆盖": "否",
    "问题说明": "模块不一致：RTM=财务中心, 页面结构=报表中心"
  },
  {
    "需求编号": "R0343",
    "需求描述": "导出功能允许用户将收支明细表数据导出为Excel、PDF等格式的文件，以便进行离线分析、存档或与其他系统进行数据交换。",
    "对应页面": "P17 账簿-收支明细表",
    "原型是否覆盖": "否",
    "问题说明": "模块不一致：RTM=财务中心, 页面结构=报表中心"
  },
  {
    "需求编号": "R0344",
    "需求描述": "打印功能可以将收支明细表以纸质形式输出，方便用户进行审核和存档。",
    "对应页面": "P17 账簿-收支明细表",
    "原型是否覆盖": "否",
    "问题说明": "模块不一致：RTM=财务中心, 页面结构=报表中心"
  },
  {
    "需求编号": "R0345",
    "需求描述": "针对村集体使用辅助核算的科目，展示其辅助核算项目的余额情况。例如，如果村集体对某些科目进行了客户、供应商等辅助核算，辅助核算余额表可以显示每个辅助核算项目的期初…",
    "对应页面": "P18 账簿-辅助核算余额表",
    "原型是否覆盖": "否",
    "问题说明": "模块不一致：RTM=财务中心, 页面结构=报表中心"
  },
  {
    "需求编号": "R0346",
    "需求描述": "辅助核算余额表应提供查询功能，用户可以根据辅助核算项目、科目等条件进行查询。查询结果应能够快速准确地呈现，并且可以进行排序和筛选。",
    "对应页面": "P18 账簿-辅助核算余额表",
    "原型是否覆盖": "否",
    "问题说明": "模块不一致：RTM=财务中心, 页面结构=报表中心"
  },
  {
    "需求编号": "R0347",
    "需求描述": "导出功能允许用户将辅助核算余额表数据导出为Excel、PDF等格式的文件，以便进行离线分析、存档或与其他系统进行数据交换。",
    "对应页面": "P18 账簿-辅助核算余额表",
    "原型是否覆盖": "否",
    "问题说明": "模块不一致：RTM=财务中心, 页面结构=报表中心"
  },
  {
    "需求编号": "R0348",
    "需求描述": "打印功能可以将辅助核算余额表以纸质形式输出，方便用户进行审核和存档。",
    "对应页面": "P18 账簿-辅助核算余额表",
    "原型是否覆盖": "否",
    "问题说明": "模块不一致：RTM=财务中心, 页面结构=报表中心"
  },
  {
    "需求编号": "R0349",
    "需求描述": "详细记录村集体使用辅助核算的科目的明细交易情况，包括辅助核算项目的信息。辅助核算明细账可以让用户深入了解每个辅助核算项目的具体交易情况，为财务分析提供更详细的数…",
    "对应页面": "P19 账簿-辅助核算明细账",
    "原型是否覆盖": "否",
    "问题说明": "模块不一致：RTM=财务中心, 页面结构=报表中心"
  },
  {
    "需求编号": "R0350",
    "需求描述": "辅助核算明细账应提供查询功能，用户可以根据辅助核算项目、科目、日期范围等条件进行查询。查询结果应能够快速准确地呈现，并且可以进行排序和筛选。",
    "对应页面": "P19 账簿-辅助核算明细账",
    "原型是否覆盖": "否",
    "问题说明": "模块不一致：RTM=财务中心, 页面结构=报表中心"
  },
  {
    "需求编号": "R0351",
    "需求描述": "导出功能允许用户将辅助核算明细账数据导出为Excel、PDF等格式的文件，以便进行离线分析、存档或与其他系统进行数据交换。",
    "对应页面": "P19 账簿-辅助核算明细账",
    "原型是否覆盖": "否",
    "问题说明": "模块不一致：RTM=财务中心, 页面结构=报表中心"
  },
  {
    "需求编号": "R0352",
    "需求描述": "打印功能可以将辅助核算明细账以纸质形式输出，方便用户进行审核和存档。",
    "对应页面": "P19 账簿-辅助核算明细账",
    "原型是否覆盖": "否",
    "问题说明": "模块不一致：RTM=财务中心, 页面结构=报表中心"
  },
  {
    "需求编号": "R0353",
    "需求描述": "综合展示村集体的财务收支情况，包括收入总额、支出总额、收支差额等信息。财务收支情况一览表可以让用户快速了解村集体的整体财务状况和收支平衡情况。",
    "对应页面": "P20 账簿-财务收支情况一览表",
    "原型是否覆盖": "否",
    "问题说明": "模块不一致：RTM=财务中心, 页面结构=报表中心"
  },
  {
    "需求编号": "R0354",
    "需求描述": "用户可以通过查询功能，根据日期范围、收入来源、支出项目等条件进行查询，以获取特定时间段或特定项目的财务收支情况。查询结果应能够快速准确地呈现，并且可以进行排序和…",
    "对应页面": "P20 账簿-财务收支情况一览表",
    "原型是否覆盖": "否",
    "问题说明": "模块不一致：RTM=财务中心, 页面结构=报表中心"
  },
  {
    "需求编号": "R0355",
    "需求描述": "可以将财务收支情况一览表以纸质形式输出，方便用户进行审核和存档。打印功能应支持用户自定义打印格式，如纸张大小、方向、边距等参数，以及打印的标题、页眉、页脚等内容…",
    "对应页面": "P20 账簿-财务收支情况一览表",
    "原型是否覆盖": "否",
    "问题说明": "模块不一致：RTM=财务中心, 页面结构=报表中心"
  },
  {
    "需求编号": "R0356",
    "需求描述": "允许用户将财务收支情况一览表数据导出为Excel、PDF等格式的文件，以便进行离线分析、存档或与其他系统进行数据交换。导出的文件应保持与财务收支情况一览表页面显…",
    "对应页面": "P20 账簿-财务收支情况一览表",
    "原型是否覆盖": "否",
    "问题说明": "模块不一致：RTM=财务中心, 页面结构=报表中心"
  },
  {
    "需求编号": "R0357",
    "需求描述": "以多栏式的形式展示村集体的财务交易情况，适用于需要对多个科目进行对比分析的情况。例如，可以设置多栏账来展示不同收入来源的明细情况，或者不同支出项目的明细情况。",
    "对应页面": "P21 账簿-多栏账",
    "原型是否覆盖": "否",
    "问题说明": "模块不一致：RTM=财务中心, 页面结构=资产管理"
  },
  {
    "需求编号": "R0358",
    "需求描述": "多栏账应提供查询功能，用户可以根据科目、日期范围等条件进行查询。查询结果应能够快速准确地呈现，并且可以进行排序和筛选。用户可以根据自己的需求选择要显示的栏目，以…",
    "对应页面": "P21 账簿-多栏账",
    "原型是否覆盖": "否",
    "问题说明": "模块不一致：RTM=财务中心, 页面结构=资产管理"
  },
  {
    "需求编号": "R0359",
    "需求描述": "可以将多栏账以纸质形式输出，方便用户进行审核和存档。打印功能应支持用户自定义打印格式，如纸张大小、方向、边距等参数，以及打印的标题、页眉、页脚等内容。",
    "对应页面": "P21 账簿-多栏账",
    "原型是否覆盖": "否",
    "问题说明": "模块不一致：RTM=财务中心, 页面结构=资产管理"
  },
  {
    "需求编号": "R0360",
    "需求描述": "允许用户将多栏账数据导出为Excel、PDF等格式的文件，以便进行离线分析、存档或与其他系统进行数据交换。导出的文件应保持与多栏账页面显示的格式一致，确保数据的…",
    "对应页面": "P21 账簿-多栏账",
    "原型是否覆盖": "否",
    "问题说明": "模块不一致：RTM=财务中心, 页面结构=资产管理"
  },
  {
    "需求编号": "R0361",
    "需求描述": "记录村集体财务操作的日志信息，包括操作时间、操作人员、操作内容等。财务日志列表可以帮助用户追溯财务操作的历史记录，便于审计和问题排查。",
    "对应页面": "P22 财务日志",
    "原型是否覆盖": "否",
    "问题说明": "模块不一致：RTM=财务中心, 页面结构=资产管理"
  },
  {
    "需求编号": "R0362",
    "需求描述": "提供查询功能，用户可以根据日期范围、操作人员、操作内容关键词等条件进行查询。查询结果应能够快速准确地呈现，并且可以进行排序和筛选。例如，用户可以按照操作时间的先…",
    "对应页面": "P22 财务日志",
    "原型是否覆盖": "否",
    "问题说明": "模块不一致：RTM=财务中心, 页面结构=资产管理"
  },
  {
    "需求编号": "R0363",
    "需求描述": "提供财务的基础设置，包括基础信息录入、账套信息设置、会计科目设置、凭证模版设置、自定义报表设置、期初设置等",
    "对应页面": "P23 基础设置",
    "原型是否覆盖": "否",
    "问题说明": "模块不一致：RTM=财务中心, 页面结构=资产管理"
  },
  {
    "需求编号": "R0364",
    "需求描述": "对村集体的财务账套进行设置，包括账套名称、会计期间、记账本位币等基本信息的设置。账套设置是财务管理系统的基础，确保财务数据的准确性和一致性。",
    "对应页面": "P23 基础设置",
    "原型是否覆盖": "否",
    "问题说明": "模块不一致：RTM=财务中心, 页面结构=资产管理"
  },
  {
    "需求编号": "R0365",
    "需求描述": "设置村集体的会计科目体系，包括科目编码、科目名称、科目类型、余额方向等。会计科目设置应符合村集体的财务管理需求和会计准则，为记账和报表编制提供规范的科目体系。",
    "对应页面": "P23 基础设置",
    "原型是否覆盖": "否",
    "问题说明": "模块不一致：RTM=财务中心, 页面结构=资产管理"
  },
  {
    "需求编号": "R0366",
    "需求描述": "提供凭证模版的设置功能，用户可以根据村集体的常见业务类型设置凭证模版，如收入凭证模版、支出凭证模版等。凭证模版可以预设摘要、科目、金额等信息，提高凭证录入的效率…",
    "对应页面": "P23 基础设置",
    "原型是否覆盖": "否",
    "问题说明": "模块不一致：RTM=财务中心, 页面结构=资产管理"
  },
  {
    "需求编号": "R0367",
    "需求描述": "允许用户根据自己的需求自定义财务报表，包括报表的格式、内容、计算公式等。自定义报表功能可以满足村集体的特殊报表需求，提高财务分析的灵活性和针对性。",
    "对应页面": "P23 基础设置",
    "原型是否覆盖": "否",
    "问题说明": "模块不一致：RTM=财务中心, 页面结构=资产管理"
  },
  {
    "需求编号": "R0368",
    "需求描述": "在财务系统启用初期，进行期初数据的录入和设置。期初设置包括资产、负债、所有者权益等科目的期初余额录入，以及其他初始设置，如往来单位期初余额、固定资产期初卡片等。…",
    "对应页面": "P23 基础设置",
    "原型是否覆盖": "否",
    "问题说明": "模块不一致：RTM=财务中心, 页面结构=资产管理"
  },
  {
    "需求编号": "R0369",
    "需求描述": "系统能够自动生成村集体的资产负债表，根据财务数据准确反映村集体的资产、负债和所有者权益状况。资产负债表的生成应符合会计准则和财务报表编制要求，确保数据的准确性和…",
    "对应页面": "P24 法定报表-资产负债表/收益及收益分配表",
    "原型是否覆盖": "否",
    "问题说明": "模块不一致：RTM=报表中心, 页面结构=资产管理"
  },
  {
    "需求编号": "R0370",
    "需求描述": "自动生成村集体的收益及收益分配表，展示村集体的经营成果和收益分配情况。收益及收益分配表的生成应包括本年收益、经营收入、投资收益、补助收入、经营支出、税金及附加、…",
    "对应页面": "P24 法定报表-资产负债表/收益及收益分配表",
    "原型是否覆盖": "否",
    "问题说明": "模块不一致：RTM=报表中心, 页面结构=资产管理"
  },
  {
    "需求编号": "R0371",
    "需求描述": "生成收益及收益分配表的管理表，提供更详细的收益分析和管理信息。管理表可以包括收益项目的明细分析、成本费用的构成分析、收益分配的比例分析等，为村集体的财务管理和决…",
    "对应页面": "P24 法定报表-资产负债表/收益及收益分配表",
    "原型是否覆盖": "否",
    "问题说明": "模块不一致：RTM=报表中心, 页面结构=资产管理"
  },
  {
    "需求编号": "R0372",
    "需求描述": "展示村集体的做账进度情况，包括已完成的凭证数量、未完成的凭证数量、审核进度等。做账进度列表可以帮助用户了解财务工作的进展情况，及时督促和协调财务人员的工作。",
    "对应页面": "P25 做账进度",
    "原型是否覆盖": "否",
    "问题说明": "模块不一致：RTM=报表中心, 页面结构=合同管理"
  },
  {
    "需求编号": "R0373",
    "需求描述": "用户可以根据行政区划和会计期间进行做账进度的查询，以便了解不同区域或不同时间段的财务工作进展情况。查询结果应能够快速准确地呈现，并且可以进行排序和筛选。",
    "对应页面": "P25 做账进度",
    "原型是否覆盖": "否",
    "问题说明": "模块不一致：RTM=报表中心, 页面结构=合同管理"
  },
  {
    "需求编号": "R0374",
    "需求描述": "可以将做账进度列表以纸质形式输出，方便用户进行审核和存档。打印功能应支持用户自定义打印格式，如纸张大小、方向、边距等参数，以及打印的标题、页眉、页脚等内容。",
    "对应页面": "P25 做账进度",
    "原型是否覆盖": "否",
    "问题说明": "模块不一致：RTM=报表中心, 页面结构=合同管理"
  },
  {
    "需求编号": "R0375",
    "需求描述": "允许用户将做账进度数据导出为Excel、PDF等格式的文件，以便进行离线分析、存档或与其他系统进行数据交换。导出的文件应保持与做账进度列表页面显示的格式一致，确…",
    "对应页面": "P25 做账进度",
    "原型是否覆盖": "否",
    "问题说明": "模块不一致：RTM=报表中心, 页面结构=合同管理"
  },
  {
    "需求编号": "R0376",
    "需求描述": "生成村集体的资产负债表统计报表，提供资产、负债和所有者权益的详细数据和分析。统计报表可以包括资产负债表的各项指标分析、同比环比分析、趋势分析等，为村集体的财务管…",
    "对应页面": "P26 统计报表-资产负债表统计",
    "原型是否覆盖": "否",
    "问题说明": "模块不一致：RTM=报表中心, 页面结构=合同管理"
  },
  {
    "需求编号": "R0377",
    "需求描述": "用户利用此功能可查看资产负债表统计报表详细内容，涵盖报表数据（如资产、负债、所有者权益各项目的具体金额）及图表分析（如资产结构、负债权益比例等直观图表展示），为…",
    "对应页面": "P26 统计报表-资产负债表统计",
    "原型是否覆盖": "否",
    "问题说明": "模块不一致：RTM=报表中心, 页面结构=合同管理"
  },
  {
    "需求编号": "R0378",
    "需求描述": "该功能支持用户将资产负债表数据导出为常见格式，如Excel、PDF等。导出后，用户可在其他软件环境中利用丰富工具对数据进行深度挖掘与分析，如运用Excel函数计…",
    "对应页面": "P26 统计报表-资产负债表统计",
    "原型是否覆盖": "否",
    "问题说明": "模块不一致：RTM=报表中心, 页面结构=合同管理"
  },
  {
    "需求编号": "R0379",
    "需求描述": "通过此打印功能，用户可将资产负债表以纸质形式输出，打印出的报表格式规范、内容清晰。这不仅满足纸质存档需求，方便日后财务追溯与审计，还便于在审核流程中直观呈现报表…",
    "对应页面": "P26 统计报表-资产负债表统计",
    "原型是否覆盖": "否",
    "问题说明": "模块不一致：RTM=报表中心, 页面结构=合同管理"
  },
  {
    "需求编号": "R0380",
    "需求描述": "生成村集体的收益及收益分配表统计报表，展示村集体的经营成果和收益分配情况。统计报表可以包括收益及收益分配表的各项指标分析、同比环比分析、趋势分析等，为村集体的财…",
    "对应页面": "P27 统计报表-收益及收益分配表统计",
    "原型是否覆盖": "否",
    "问题说明": "模块不一致：RTM=报表中心, 页面结构=合同管理"
  },
  {
    "需求编号": "R0381",
    "需求描述": "用户能够通过该功能查看收益及收益分配表统计报表的详细内容。这使他们可以清晰地了解收益的来源、分配情况等相关信息，为财务分析和决策提供数据支持。",
    "对应页面": "P27 统计报表-收益及收益分配表统计",
    "原型是否覆盖": "否",
    "问题说明": "模块不一致：RTM=报表中心, 页面结构=合同管理"
  },
  {
    "需求编号": "R0382",
    "需求描述": "此功能允许用户将收益及收益分配表的数据导出。用户可以选择合适的文件格式，如Excel、PDF等进行导出，方便在其他软件中进行进一步的数据处理、分析或存档，也便于…",
    "对应页面": "P27 统计报表-收益及收益分配表统计",
    "原型是否覆盖": "否",
    "问题说明": "模块不一致：RTM=报表中心, 页面结构=合同管理"
  },
  {
    "需求编号": "R0383",
    "需求描述": "通过打印功能，用户可以将收益及收益分配表以纸质形式输出。这在需要纸质存档、审核或者在会议等场合展示报表内容时非常有用，能够确保报表内容准确、清晰地呈现出来",
    "对应页面": "P27 统计报表-收益及收益分配表统计",
    "原型是否覆盖": "否",
    "问题说明": "模块不一致：RTM=报表中心, 页面结构=合同管理"
  },
  {
    "需求编号": "R0384",
    "需求描述": "生成村集体的科目汇总表统计报表，展示各个会计科目的借贷方发生额合计。统计报表可以包括科目汇总表的各项指标分析、同比环比分析、趋势分析等，为村集体的财务管理和决策…",
    "对应页面": "P28 统计报表-科目汇总表统计",
    "原型是否覆盖": "否",
    "问题说明": "模块不一致：RTM=报表中心, 页面结构=在线审批"
  },
  {
    "需求编号": "R0385",
    "需求描述": "用户可通过此功能查看统计报表中的科目汇总表详细内容。这使他们能够直观地了解各个科目的汇总数据，例如科目余额、借贷方发生额等，为财务分析和决策提供数据基础。",
    "对应页面": "P28 统计报表-科目汇总表统计",
    "原型是否覆盖": "否",
    "问题说明": "模块不一致：RTM=报表中心, 页面结构=在线审批"
  },
  {
    "需求编号": "R0386",
    "需求描述": "该功能允许用户将科目汇总表数据导出。用户可以选择将数据导出为常见格式，如Excel、PDF等，便于在其他软件中进行进一步的数据处理、分析或存档，也方便与其他部门…",
    "对应页面": "P28 统计报表-科目汇总表统计",
    "原型是否覆盖": "否",
    "问题说明": "模块不一致：RTM=报表中心, 页面结构=在线审批"
  },
  {
    "需求编号": "R0387",
    "需求描述": "通过此打印功能，用户能够将科目汇总表以纸质形式输出。这在需要纸质存档、审核或在会议等场合展示报表内容时非常有用，确保报表内容能够准确、清晰地呈现",
    "对应页面": "P28 统计报表-科目汇总表统计",
    "原型是否覆盖": "否",
    "问题说明": "模块不一致：RTM=报表中心, 页面结构=在线审批"
  },
  {
    "需求编号": "R0388",
    "需求描述": "生成村集体的科目汇总表明细表统计报表，详细展示各个会计科目的明细交易情况。统计报表可以包括科目汇总表明细表的各项指标分析、同比环比分析、趋势分析等，为村集体的财…",
    "对应页面": "P29 统计报表-科目汇总表明细统计",
    "原型是否覆盖": "否",
    "问题说明": "模块不一致：RTM=报表中心, 页面结构=在线审批"
  },
  {
    "需求编号": "R0389",
    "需求描述": "用户能够通过该功能查看科目汇总表明细表统计报表的详细内容。这意味着用户可以清晰地了解每个科目的具体情况，包括但不限于科目余额、发生额等信息，从而为财务分析和决策…",
    "对应页面": "P29 统计报表-科目汇总表明细统计",
    "原型是否覆盖": "否",
    "问题说明": "模块不一致：RTM=报表中心, 页面结构=在线审批"
  },
  {
    "需求编号": "R0390",
    "需求描述": "此功能允许用户将科目汇总表明细表统计报表的数据导出。用户可以选择将数据导出为常见的文件格式，如Excel、PDF等，方便在其他软件中进行进一步的数据处理、分析或…",
    "对应页面": "P29 统计报表-科目汇总表明细统计",
    "原型是否覆盖": "否",
    "问题说明": "模块不一致：RTM=报表中心, 页面结构=在线审批"
  },
  {
    "需求编号": "R0391",
    "需求描述": "通过打印功能，用户可以将科目汇总表明细表统计报表以纸质形式输出。这对于需要纸质存档、审核或在会议等场合展示报表内容的情况非常有用，能够确保报表内容准确、清晰地呈…",
    "对应页面": "P29 统计报表-科目汇总表明细统计",
    "原型是否覆盖": "否",
    "问题说明": "模块不一致：RTM=报表中心, 页面结构=在线审批"
  },
  {
    "需求编号": "R0392",
    "需求描述": "在统计报表科目汇总表中展示未结账的科目数量。这一功能可以帮助用户及时了解财务工作的进度，确保所有科目都能按时结账。",
    "对应页面": "P30 统计报表-未结账数量",
    "原型是否覆盖": "否",
    "问题说明": "模块不一致：RTM=报表中心, 页面结构=在线审批"
  },
  {
    "需求编号": "R0393",
    "需求描述": "提供对村委会的资产进行卡片式管理，将资产的详细信息，以资产列表形式展现。如资产编号、名称、型号、入账日期和原值等信息输入系统，方便管理者跟踪和管理，系统还提供包…",
    "对应页面": "P31 资产台账",
    "原型是否覆盖": "否",
    "问题说明": "模块不一致：RTM=资产管理, 页面结构=银农直联"
  },
  {
    "需求编号": "R0394",
    "需求描述": "资产列表以表格形式展示村委会资产信息，用户可通过筛选查询获取所需资产详情，其数据与其他模块关联，为资产管理和相关操作提供基础数据支持。",
    "对应页面": "P31 资产台账",
    "原型是否覆盖": "否",
    "问题说明": "模块不一致：RTM=资产管理, 页面结构=银农直联"
  },
  {
    "需求编号": "R0395",
    "需求描述": "资产新增功能用于录入新资产信息，用户需填写各项必填信息，经系统验证后保存，新增资产信息将更新至相关模块，确保资产管理数据的及时和完整。",
    "对应页面": "P31 资产台账",
    "原型是否覆盖": "否",
    "问题说明": "模块不一致：RTM=资产管理, 页面结构=银农直联"
  },
  {
    "需求编号": "R0396",
    "需求描述": "当资产信息变动时，资产修改功能允许用户编辑除资产编号外的信息，修改后经系统验证更新数据库，同时影响相关模块数据，保证资产信息的准确性。",
    "对应页面": "P31 资产台账",
    "原型是否覆盖": "否",
    "问题说明": "模块不一致：RTM=资产管理, 页面结构=银农直联"
  },
  {
    "需求编号": "R0397",
    "需求描述": "资产删除功能可在特定情况下将资产信息从系统移除，操作前系统检查关联数据，无关联时直接删除，存在关联则需先处理，确保数据完整性和管理准确性。",
    "对应页面": "P31 资产台账",
    "原型是否覆盖": "否",
    "问题说明": "模块不一致：RTM=资产管理, 页面结构=银农直联"
  },
  {
    "需求编号": "R0398",
    "需求描述": "资产导出功能可将资产列表数据转换为常见文件格式，用户选择格式并指定保存路径后即可导出，导出数据与资产列表关联，方便离线分析和数据交换。",
    "对应页面": "P31 资产台账",
    "原型是否覆盖": "否",
    "问题说明": "模块不一致：RTM=资产管理, 页面结构=银农直联"
  },
  {
    "需求编号": "R0399",
    "需求描述": "资产列表打印功能可将资产列表以纸质形式输出，用户通过打印设置后可打印存档或审核，打印内容与资产列表数据一致，满足日常管理和审计需求。",
    "对应页面": "P31 资产台账",
    "原型是否覆盖": "否",
    "问题说明": "模块不一致：RTM=资产管理, 页面结构=银农直联"
  },
  {
    "需求编号": "R0400",
    "需求描述": "资产汇总列表从宏观汇总展示村委会资产总体状况，包括资产总值、各类资产数量占比等信息，数据实时更新，为决策提供支持并关联资产报表生成。",
    "对应页面": "P31 资产台账",
    "原型是否覆盖": "否",
    "问题说明": "模块不一致：RTM=资产管理, 页面结构=银农直联"
  },
  {
    "需求编号": "R0401",
    "需求描述": "资产折旧列表展示资产折旧计算明细，用户可查询特定资产或时间段的折旧情况，其数据源于资产信息，用于跟踪管理折旧和确保财务核算准确。提供按照资产的折旧方法及原值、残…",
    "对应页面": "P32 资产折旧",
    "原型是否覆盖": "否",
    "问题说明": "模块不一致：RTM=资产管理, 页面结构=基层党建"
  },
  {
    "需求编号": "R0402",
    "需求描述": "对村集体的固定资产进行折旧计提，按照预设的折旧方法和年限计算资产的折旧额。计提折旧功能可以确保资产价值的准确反映，为财务报表提供准确的数据。",
    "对应页面": "P32 资产折旧",
    "原型是否覆盖": "否",
    "问题说明": "模块不一致：RTM=资产管理, 页面结构=基层党建"
  },
  {
    "需求编号": "R0403",
    "需求描述": "在计提折旧后，系统可以一键生成折旧凭证，方便财务记账。折旧凭证应包括折旧的金额、资产名称、折旧方法等信息，确保财务数据的准确性和一致性。",
    "对应页面": "P32 资产折旧",
    "原型是否覆盖": "否",
    "问题说明": "模块不一致：RTM=资产管理, 页面结构=基层党建"
  },
  {
    "需求编号": "R0404",
    "需求描述": "可以将资产折旧的相关信息打印出来，方便用户进行审核和存档。打印内容可以包括折旧计算表、折旧凭证等。",
    "对应页面": "P32 资产折旧",
    "原型是否覆盖": "否",
    "问题说明": "模块不一致：RTM=资产管理, 页面结构=基层党建"
  },
  {
    "需求编号": "R0405",
    "需求描述": "将资产折旧的相关信息导出为文件，方便进行离线分析和与其他系统进行数据交换。导出的文件格式可以选择Excel、PDF等。",
    "对应页面": "P32 资产折旧",
    "原型是否覆盖": "否",
    "问题说明": "模块不一致：RTM=资产管理, 页面结构=基层党建"
  },
  {
    "需求编号": "R0406",
    "需求描述": "在必要时，用户可以删除资产折旧的相关信息。但应谨慎操作，确保不会误删重要数据。删除前应进行确认提示，防止误操作。",
    "对应页面": "P32 资产折旧",
    "原型是否覆盖": "否",
    "问题说明": "模块不一致：RTM=资产管理, 页面结构=基层党建"
  },
  {
    "需求编号": "R0407",
    "需求描述": "系统提供将资产的新增、变更、处置、折旧一键生成财务的凭证，减少财务工作者的工作量，提升工作效率。",
    "对应页面": "P32 资产折旧",
    "原型是否覆盖": "否",
    "问题说明": "模块不一致：RTM=资产管理, 页面结构=基层党建"
  },
  {
    "需求编号": "R0408",
    "需求描述": "对资产进行结账操作，将资产的当前状态进行锁定，确保财务数据的准确性和稳定性。资产结账后，不能再对已结账期间的资产进行修改，除非进行反结账操作。结账前，系统应进行…",
    "对应页面": "P33 资产结账",
    "原型是否覆盖": "否",
    "问题说明": "RTM映射页面 P33 不在页面结构JSON中"
  },
  {
    "需求编号": "R0409",
    "需求描述": "资产结账列表主要展示村集体资产结账的相关信息，其功能丰富多样。用户可查看各账套在不同会计期间的结账状态。操作栏提供结账与反结账功能，结账前系统自动检查数据完整性…",
    "对应页面": "P33 资产结账",
    "原型是否覆盖": "否",
    "问题说明": "RTM映射页面 P33 不在页面结构JSON中"
  },
  {
    "需求编号": "R0410",
    "需求描述": "在必要时，用户可以对已结账的资产进行反结账操作，以便对资产数据进行调整和修改。但应谨慎操作，确保反结账后的资产数据能够正确反映实际情况。反结账前，系统应进行提示…",
    "对应页面": "P33 资产结账",
    "原型是否覆盖": "否",
    "问题说明": "RTM映射页面 P33 不在页面结构JSON中"
  },
  {
    "需求编号": "R0411",
    "需求描述": "资产明细表功能模块通过列表形式详细呈现各类资产的具体信息，包括所属区域、资产名称、资产编号、资产类型、资产规格、入账日期、入账金额、本期折旧、累计折旧、账面价值…",
    "对应页面": "P34 资产报表",
    "原型是否覆盖": "否",
    "问题说明": "RTM映射页面 P34 不在页面结构JSON中"
  },
  {
    "需求编号": "R0412",
    "需求描述": "资产报表-折旧汇总表功能模块主要是对资产折旧情况进行汇总统计。它将各类资产的折旧数据整理汇总，展示出资产在特定时间范围内的折旧总额以及不同资产类型的折旧分布等信…",
    "对应页面": "P34 资产报表",
    "原型是否覆盖": "否",
    "问题说明": "RTM映射页面 P34 不在页面结构JSON中"
  },
  {
    "需求编号": "R0413",
    "需求描述": "以列表形式展示村集体的所有合同信息，包括合同编号、合同名称、签订日期、合同金额、合同期限、合同状态等。用户可以通过合同管理列表快速了解村集体的合同情况，进行合同…",
    "对应页面": "P35 合同台账",
    "原型是否覆盖": "否",
    "问题说明": "RTM映射页面 P35 不在页面结构JSON中"
  },
  {
    "需求编号": "R0414",
    "需求描述": "用户可以在系统中新增合同信息，包括合同的基本信息、合同条款、附件等。新增合同应确保信息的准确性和完整性，为合同管理提供基础数据。",
    "对应页面": "P35 合同台账",
    "原型是否覆盖": "否",
    "问题说明": "RTM映射页面 P35 不在页面结构JSON中"
  },
  {
    "需求编号": "R0415",
    "需求描述": "当合同信息发生变化时，用户可以对合同进行修改。修改合同应确保修改后的信息准确反映实际情况，同时保留修改的历史记录，方便追溯和审计。",
    "对应页面": "P35 合同台账",
    "原型是否覆盖": "否",
    "问题说明": "RTM映射页面 P35 不在页面结构JSON中"
  },
  {
    "需求编号": "R0416",
    "需求描述": "对合同的执行情况进行验收，确保合同的履行符合约定。合同验收应包括验收的标准、验收的结果等信息，为合同管理提供监督和保障。",
    "对应页面": "P35 合同台账",
    "原型是否覆盖": "否",
    "问题说明": "RTM映射页面 P35 不在页面结构JSON中"
  },
  {
    "需求编号": "R0417",
    "需求描述": "在必要时，用户可以取消合同的验收结果，重新进行验收。取消验收应进行确认提示，防止误操作。",
    "对应页面": "P35 合同台账",
    "原型是否覆盖": "否",
    "问题说明": "RTM映射页面 P35 不在页面结构JSON中"
  },
  {
    "需求编号": "R0418",
    "需求描述": "当合同履行完毕或出现其他情况需要终止合同时，用户可以进行合同终止操作。合同终止应包括终止的原因、终止的时间等信息，为合同管理提供规范的流程。",
    "对应页面": "P35 合同台账",
    "原型是否覆盖": "否",
    "问题说明": "RTM映射页面 P35 不在页面结构JSON中"
  },
  {
    "需求编号": "R0419",
    "需求描述": "在特殊情况下，用户可以取消合同的终止状态，重新恢复合同的执行。取消终止应进行确认提示，防止误操作。",
    "对应页面": "P35 合同台账",
    "原型是否覆盖": "否",
    "问题说明": "RTM映射页面 P35 不在页面结构JSON中"
  },
  {
    "需求编号": "R0420",
    "需求描述": "在必要时，用户可以删除合同信息。但应谨慎操作，确保不会误删重要合同。删除前应进行确认提示，防止误操作。",
    "对应页面": "P35 合同台账",
    "原型是否覆盖": "否",
    "问题说明": "RTM映射页面 P35 不在页面结构JSON中"
  },
  {
    "需求编号": "R0421",
    "需求描述": "对合同的收付款情况进行管理，包括实际收款日期、实际收款金额、关联凭证号等信息的填写。合同收付款应确保财务数据的准确性和及时性，为合同管理提供资金支持。",
    "对应页面": "P35 合同台账",
    "原型是否覆盖": "否",
    "问题说明": "RTM映射页面 P35 不在页面结构JSON中"
  },
  {
    "需求编号": "R0422",
    "需求描述": "用户可以填写合同的实际收款日期，确保收付款信息的准确性和及时性。",
    "对应页面": "P35 合同台账",
    "原型是否覆盖": "否",
    "问题说明": "RTM映射页面 P35 不在页面结构JSON中"
  },
  {
    "需求编号": "R0423",
    "需求描述": "用户可以填写合同的实际收款金额，记录合同的资金流入情况。",
    "对应页面": "P35 合同台账",
    "原型是否覆盖": "否",
    "问题说明": "RTM映射页面 P35 不在页面结构JSON中"
  },
  {
    "需求编号": "R0424",
    "需求描述": "用户可以填写合同收付款的关联凭证号，方便与财务系统进行数据核对和追溯。",
    "对应页面": "P35 合同台账",
    "原型是否覆盖": "否",
    "问题说明": "RTM映射页面 P35 不在页面结构JSON中"
  },
  {
    "需求编号": "R0425",
    "需求描述": "当合同到期需要续签时，用户可以进行合同续签操作。合同续签应包括续签的条款、续签的期限等信息，为合同管理提供延续性。",
    "对应页面": "P35 合同台账",
    "原型是否覆盖": "否",
    "问题说明": "RTM映射页面 P35 不在页面结构JSON中"
  },
  {
    "需求编号": "R0426",
    "需求描述": "提供合同列表的查询功能，用户可以根据合同的不同属性进行查询，快速定位所需的合同信息。",
    "对应页面": "P35 合同台账",
    "原型是否覆盖": "否",
    "问题说明": "RTM映射页面 P35 不在页面结构JSON中"
  },
  {
    "需求编号": "R0427",
    "需求描述": "为用户提供合同导入的模版，方便用户批量导入合同信息。合同导入模版应包括合同的基本信息、合同条款、附件等字段，确保导入数据的格式一致性和准确性。",
    "对应页面": "P35 合同台账",
    "原型是否覆盖": "否",
    "问题说明": "RTM映射页面 P35 不在页面结构JSON中"
  },
  {
    "需求编号": "R0428",
    "需求描述": "支持用户将外部的合同数据导入到系统中，提高合同管理的效率。合同导入可以选择不同的文件格式，如Excel、CSV等。",
    "对应页面": "P35 合同台账",
    "原型是否覆盖": "否",
    "问题说明": "RTM映射页面 P35 不在页面结构JSON中"
  },
  {
    "需求编号": "R0429",
    "需求描述": "允许用户将合同信息导出为文件，方便进行离线分析和与其他系统进行数据交换。合同导出可以选择不同的文件格式，如Excel、PDF等。",
    "对应页面": "P35 合同台账",
    "原型是否覆盖": "否",
    "问题说明": "RTM映射页面 P35 不在页面结构JSON中"
  },
  {
    "需求编号": "R0430",
    "需求描述": "提供对村委会的合同内容进行变更功能。对合同的变更情况进行管理，以列表形式展示合同变更的记录。合同变更管理列表应包括变更的合同编号、变更日期、变更内容、变更原因等…",
    "对应页面": "P36 合同变更",
    "原型是否覆盖": "否",
    "问题说明": "RTM映射页面 P36 不在页面结构JSON中"
  },
  {
    "需求编号": "R0431",
    "需求描述": "页面提供了变更操作入口，用户可以对选定的合同进行变更操作。用户填写变更内容、变更原因等必要信息，并记录变更日期。这确保了合同变更过程的可追溯性和规范性。例如，当…",
    "对应页面": "P36 合同变更",
    "原型是否覆盖": "否",
    "问题说明": "RTM映射页面 P36 不在页面结构JSON中"
  },
  {
    "需求编号": "R0432",
    "需求描述": "生成合同收款报表，详细展示合同的收款情况。收款报表可以包括合同编号、收款日期、收款金额、收款方式、未收款金额等信息。收款报表可以以表格的形式呈现，清晰地列出每个…",
    "对应页面": "P37 合同收款报表",
    "原型是否覆盖": "否",
    "问题说明": "RTM映射页面 P37 不在页面结构JSON中"
  },
  {
    "需求编号": "R0433",
    "需求描述": "提供合同收付款的总览报表，综合展示合同的收款和付款情况。总览表可以包括合同编号、收款金额、付款金额、收支差额等信息。总览表可以帮助用户全面了解合同的资金流动情况…",
    "对应页面": "P38 合同收付款总览",
    "原型是否覆盖": "否",
    "问题说明": "RTM映射页面 P38 不在页面结构JSON中"
  },
  {
    "需求编号": "R0434",
    "需求描述": "生成合同付款报表，展示合同的付款情况。付款报表可以包括合同编号、付款日期、付款金额、付款方式、未付款金额等信息。付款报表的格式和功能与收款报表类似，以表格形式列…",
    "对应页面": "P39 合同付款报表",
    "原型是否覆盖": "否",
    "问题说明": "RTM映射页面 P39 不在页面结构JSON中"
  },
  {
    "需求编号": "R0435",
    "需求描述": "对村集体的各项业务进行在线审批管理，确保业务的合法性和规范性。在线审批管理应包括操作流程、支付管理、审批中心、审批岗位、审批流程、审批岗位流程、收支类型、历史审…",
    "对应页面": "P40 支付管理",
    "原型是否覆盖": "否",
    "问题说明": "RTM映射页面 P40 不在页面结构JSON中"
  },
  {
    "需求编号": "R0436",
    "需求描述": "明确在线审批的操作流程，为用户提供清晰的审批指南。操作流程应包括申请提交、审批流转、审批结果通知等环节。操作流程可以以流程图的形式展示，让用户直观地了解审批的各…",
    "对应页面": "P40 支付管理",
    "原型是否覆盖": "否",
    "问题说明": "RTM映射页面 P40 不在页面结构JSON中"
  },
  {
    "需求编号": "R0437",
    "需求描述": "对村集体的支付业务进行管理，包括新增支付单和审批流程。支付管理应确保支付的合法性和准确性，防止资金风险。新增支付单时，用户应填写支付的相关信息，如支付金额、支付…",
    "对应页面": "P40 支付管理",
    "原型是否覆盖": "否",
    "问题说明": "RTM映射页面 P40 不在页面结构JSON中"
  },
  {
    "需求编号": "R0438",
    "需求描述": "支付列表是支付管理模块的重要组成部分，用于展示村集体所有支付相关记录。它以表格形式呈现，内容包括序号、单号、支付状态、支付金额、支付日期、支付对象、财务主体等多…",
    "对应页面": "P40 支付管理",
    "原型是否覆盖": "否",
    "问题说明": "RTM映射页面 P40 不在页面结构JSON中"
  },
  {
    "需求编号": "R0439",
    "需求描述": "提供审批中心功能，审批人可以在审批中心查看待审批的支付单和其他审批事项，进行审批操作。审批中心应集中展示待审批的事项，方便审批人快速处理。审批人可以点击待审批事…",
    "对应页面": "P41 审批中心",
    "原型是否覆盖": "否",
    "问题说明": "RTM映射页面 P41 不在页面结构JSON中"
  },
  {
    "需求编号": "R0440",
    "需求描述": "审批中心列表作为审批流程管理的核心展示区域，在财务审批体系中占据关键地位。它以表格形式呈现，包含“序号”“收款单位”“收款账号”“摘要”“审核人”“单据审批状态…",
    "对应页面": "P41 审批中心",
    "原型是否覆盖": "否",
    "问题说明": "RTM映射页面 P41 不在页面结构JSON中"
  },
  {
    "需求编号": "R0441",
    "需求描述": "设置审批岗位，明确不同岗位的审批权限和职责。审批岗位可以根据村集体的组织架构和业务需求进行设置。审批岗位的设置应考虑审批的层级和专业性，确保审批的合理性和有效性…",
    "对应页面": "P42 审批配置",
    "原型是否覆盖": "否",
    "问题说明": "RTM映射页面 P42 不在页面结构JSON中"
  },
  {
    "需求编号": "R0442",
    "需求描述": "定义审批的流程和顺序，确保审批的规范和高效。审批流程可以根据不同的业务类型和审批事项进行设置。审批流程应明确各个审批环节的参与人员和审批时间要求，确保审批的及时…",
    "对应页面": "P42 审批配置",
    "原型是否覆盖": "否",
    "问题说明": "RTM映射页面 P42 不在页面结构JSON中"
  },
  {
    "需求编号": "R0443",
    "需求描述": "结合审批岗位和审批流程，明确每个审批岗位在审批流程中的具体职责和操作步骤。审批岗位流程可以以流程图的形式展示，让每个审批岗位的人员清楚地了解自己在审批过程中的角…",
    "对应页面": "P42 审批配置",
    "原型是否覆盖": "否",
    "问题说明": "RTM映射页面 P42 不在页面结构JSON中"
  },
  {
    "需求编号": "R0444",
    "需求描述": "对村集体的收支类型进行分类管理，方便审批和财务统计。收支类型可以包括收入类型和支出类型。收入类型可以进一步细分为经营收入、补助收入、投资收益等；支出类型可以细分…",
    "对应页面": "P42 审批配置",
    "原型是否覆盖": "否",
    "问题说明": "RTM映射页面 P42 不在页面结构JSON中"
  },
  {
    "需求编号": "R0445",
    "需求描述": "记录村集体的历史审批事项，方便查询和审计。历史审批应包括审批的事项、审批人、审批时间、审批结果等信息。历史审批记录可以以列表的形式展示，用户可以通过筛选和排序功…",
    "对应页面": "P43 历史审批与支付记录",
    "原型是否覆盖": "否",
    "问题说明": "RTM映射页面 P43 不在页面结构JSON中"
  },
  {
    "需求编号": "R0446",
    "需求描述": "记录村集体的支付记录，包括支付的金额、支付对象、支付时间、支付方式等信息。支付记录应与财务系统进行数据同步，确保支付信息的准确性和及时性。支付记录可以以表格的形…",
    "对应页面": "P43 历史审批与支付记录",
    "原型是否覆盖": "否",
    "问题说明": "RTM映射页面 P43 不在页面结构JSON中"
  },
  {
    "需求编号": "R0447",
    "需求描述": "实现银行接口设置功能，具体包括新增、删除、修改、查询。所涉及的信息包含银行类型名称、银行ip、加密端口、服务地址、FTP地址、FTP端口、FTP登录名、FTP登…",
    "对应页面": "P44 银行接口设置",
    "原型是否覆盖": "否",
    "问题说明": "RTM映射页面 P44 不在页面结构JSON中"
  },
  {
    "需求编号": "R0448",
    "需求描述": "负责村集体基本账户的全面管理，包括账户的创建、维护和监控等操作。页面可能以列表展示账户编号、账户名称、开户银行、账户余额等基本账户信息，具备账户的新增、修改、删…",
    "对应页面": "P45 基本账户管理",
    "原型是否覆盖": "否",
    "问题说明": "RTM映射页面 P45 不在页面结构JSON中"
  },
  {
    "需求编号": "R0449",
    "需求描述": "用于查询村集体基本账户的余额情况，为财务决策提供数据支持。页面可能直观显示账户的当前余额、可用余额、冻结金额等关键数据，并且可能支持按时间段查询余额历史记录，通…",
    "对应页面": "P46 账户余额查询",
    "原型是否覆盖": "否",
    "问题说明": "RTM映射页面 P46 不在页面结构JSON中"
  },
  {
    "需求编号": "R0450",
    "需求描述": "开户银行模块用于管理村集体在各银行的开户信息，以列表形式展示银行名称、银行账号、开户日期、账户类型等相关信息，便于财务人员查看和核对。该模块支持新增、修改、删除…",
    "对应页面": "P47 开户银行管理",
    "原型是否覆盖": "否",
    "问题说明": "RTM映射页面 P47 不在页面结构JSON中"
  },
  {
    "需求编号": "R0451",
    "需求描述": "主要用于管理村集体的业务往来单位信息，通过列表展示序号、往来单位名称、联系人、联系方式、账号等详细资料。该页面可能具备新增、编辑、删除往来单位信息的操作按钮，还…",
    "对应页面": "P48 往来单位管理",
    "原型是否覆盖": "否",
    "问题说明": "RTM映射页面 P48 不在页面结构JSON中"
  },
  {
    "需求编号": "R0452",
    "需求描述": "专注于管理村集体与个人的财务往来信息，以表格形式呈现序号、个人姓名、联系方式、业务类型、金额等关键数据。此页面提供添加、修改、删除往来个人信息的操作功能，同时可…",
    "对应页面": "P49 个人往来管理",
    "原型是否覆盖": "否",
    "问题说明": "RTM映射页面 P49 不在页面结构JSON中"
  },
  {
    "需求编号": "R0453",
    "需求描述": "此模块用于记录和管理银行电子回单的下载情况，方便财务人员追溯和查询。页面以表格形式展示下载记录，包括下载日期、下载人员、银行账号、回单类型、回单日期等信息。该模…",
    "对应页面": "P50 电子回单下载记录",
    "原型是否覆盖": "否",
    "问题说明": "RTM映射页面 P50 不在页面结构JSON中"
  },
  {
    "需求编号": "R0454",
    "需求描述": "党组织管理模块具有统一规范的党组织数据采集；树型管理党组织机构，将展示出上级党组织；下级党组织信息以及基层组织信息完整度情况；为党组织提供数据依据的同时，形成区…",
    "对应页面": "P51 党组织管理",
    "原型是否覆盖": "否",
    "问题说明": "RTM映射页面 P51 不在页面结构JSON中"
  },
  {
    "需求编号": "R0455",
    "需求描述": "对村集体的党员基础信息进行维护，包括党员姓名、性别、年龄、入党时间等。党员管理基础信息维护应确保党员信息的准确性和及时性。用户可以在系统中添加、修改和删除党员基…",
    "对应页面": "P52 党员基础信息",
    "原型是否覆盖": "否",
    "问题说明": "RTM映射页面 P52 不在页面结构JSON中"
  },
  {
    "需求编号": "R0456",
    "需求描述": "管理村集体党员的组织关系信息，包括党员的转入、转出、内部调动等。党员管理组织关系信息维护应确保组织关系的清晰和准确。用户可以在系统中办理党员的组织关系转移手续，…",
    "对应页面": "P53 组织关系管理",
    "原型是否覆盖": "否",
    "问题说明": "RTM映射页面 P53 不在页面结构JSON中"
  },
  {
    "需求编号": "R0457",
    "需求描述": "三严三实：党员可以在线学习三严三实课程内容；两学一做：党员可以在线学习两学一做课程内容、三会一课：党员可以在线学习三会一课课程内容；网络课堂进行在线学习，学习进…",
    "对应页面": "P54 党建学习专题",
    "原型是否覆盖": "否",
    "问题说明": "RTM映射页面 P54 不在页面结构JSON中"
  },
  {
    "需求编号": "R0458",
    "需求描述": "提供党员在线学习功能，包括学习课程的发布、学习进度的跟踪、学习成绩的记录等。学习管理在线学习应方便党员随时随地进行学习，提高党员的政治素质和业务能力。系统可以发…",
    "对应页面": "P55 在线学习",
    "原型是否覆盖": "否",
    "问题说明": "RTM映射页面 P55 不在页面结构JSON中"
  },
  {
    "需求编号": "R0459",
    "需求描述": "记录党员的学习进度，方便党员和管理人员了解学习情况。学习进度记录应包括学习课程的完成情况、学习时间的统计等。系统可以以图表或列表的形式展示党员的学习进度，让党员…",
    "对应页面": "P56 学习进度",
    "原型是否覆盖": "否",
    "问题说明": "RTM映射页面 P56 不在页面结构JSON中"
  },
  {
    "需求编号": "R0460",
    "需求描述": "党员可以在学习过程中记录学习笔记，方便复习和交流。学习笔记管理应支持笔记的添加、修改、删除和查询。系统应提供学习笔记的编辑功能，让党员可以方便地记录学习心得和体…",
    "对应页面": "P57 学习笔记",
    "原型是否覆盖": "否",
    "问题说明": "RTM映射页面 P57 不在页面结构JSON中"
  },
  {
    "需求编号": "R0461",
    "需求描述": "党员可以对学习课程进行评价，为课程的改进和优化提供参考。课程评价管理应支持评价的提交、查看和统计。系统应提供课程评价的入口，让党员可以对学习课程进行评价。评价内…",
    "对应页面": "P58 课程评价",
    "原型是否覆盖": "否",
    "问题说明": "RTM映射页面 P58 不在页面结构JSON中"
  },
  {
    "需求编号": "R0462",
    "需求描述": "组织党员进行在线考试，检验学习效果。在线考试管理应包括考试的组织、试卷的生成、考试成绩的统计等。系统可以根据学习内容自动生成考试试卷，党员可以在线参加考试。考试…",
    "对应页面": "P59 在线考试",
    "原型是否覆盖": "否",
    "问题说明": "RTM映射页面 P59 不在页面结构JSON中"
  }
]